{
    "task_1_name": "Решалки квадратных уравнений",
    "task_2_name": "Решалки квадратных уравнений на JS",
    "task_3_name": "Модули для Sublime Text 3",


    "task_1": [
      {
        "name": "Решалка кв. уравнений (для консоли)",
        "img": "img/ProjectPreview/task1(0).png",
        "price": "",
        "url": "./task/QuadraticEquations(0).py"
      },
      {
        "name": "Решалка кв. уравнений",
        "img": "img/ProjectPreview/task1(1).png",
        "price": "",
        "url": "./task/QuadraticEquations(1).py"
      }
    ],
    "task_2": [
        {
          "name": "JS Решалка кв. уравнений 1",
          "img": "",
          "price": "",
          "url": ""
        },
        {
          "name": "",
          "img": "",
          "price": "",
          "url": ""
        },
        {
          "name": "",
          "img": "",
          "price": "",
          "url": ""
        }
      ],
      "task_3": [
        {
          "name": "Модуль 'Hello world'",
          "img": "",
          "price": "",
          "url": ""
        }
      ]
  }
